Workspace/Sonar/8-bit UART/Uart8.v
// Adjusted UART Receiver Module
module Uart8Receiver #(
    parameter RX_OVERSAMPLE_RATE = 16
)(
    input wire clk,
    input wire rxClk, // Use rxClk from top-level
    input wire en,
    input wire in,
    output reg busy,
    output reg done,
    output reg err,
    output reg [7:0] out
);

    // States for the receiver FSM
    localparam IDLE = 0;
    localparam START = 1;
    localparam DATA = 2;
    localparam STOP = 3;

    reg [2:0] state = IDLE;

    // Counter for oversampling
    reg [3:0] oversampleCounter = 0;

    // Data register
    reg [7:0] data = 0;

    // Bit counter
    reg [2:0] bitCounter = 0;

    always @(posedge rxClk) begin
        case (state)
            IDLE: begin
                busy <= 0;
                done <= 0;
                err <= 0;
                if (en && in == 0) begin // Start bit detected
                    state <= START;
                    oversampleCounter <= 0;
                end
            end

            START: begin
                if (oversampleCounter == RX_OVERSAMPLE_RATE / 2 - 1) begin
                    if (in == 0) begin // Start bit confirmed
                        state <= DATA;
                        oversampleCounter <= 0;
                        bitCounter <= 0;
                    end else begin // Error: Not a start bit
                        state <= IDLE;
                        err <= 1;
                    end
                end else begin
                    oversampleCounter <= oversampleCounter + 1;
                end
            end

            DATA: begin
                if (oversampleCounter == RX_OVERSAMPLE_RATE / 2 - 1) begin
                    data[7 - bitCounter] <= in;
                    bitCounter <= bitCounter + 1;
                    oversampleCounter <= 0;
                    if (bitCounter == 8) begin
                        state <= STOP;
                    end
                end else begin
                    oversampleCounter <= oversampleCounter + 1;
                end
            end

            STOP: begin
                if (oversampleCounter == RX_OVERSAMPLE_RATE / 2 - 1) begin
                    if (in == 1) begin // Stop bit confirmed
                        state <= IDLE;
                        busy <= 1;
                        done <= 1;
                        out <= data;
                    end else begin // Error: Not a stop bit
                        state <= IDLE;
                        err <= 1;
                    end
                end else begin
                    oversampleCounter <= oversampleCounter + 1;
                end
            end

            default: state <= IDLE;
        endcase
    end

    always @(posedge clk) begin
        if (state == IDLE) begin
            busy <= 0;
        end else begin
            busy <= 1;
        end
    end

endmodule

// Adjusted UART Transmitter Module
module Uart8Transmitter #(
    parameter TURBO_FRAMES = 0
)(
    input wire clk,
    input wire txClk, // Use txClk from top-level
    input wire en,
    input wire start,
    input wire [7:0] in,
    output reg busy,
    output reg done,
    output reg out
);

    // States for the transmitter FSM
    localparam IDLE = 0;
    localparam START = 1;
    localparam DATA = 2;
    localparam STOP = 3;

    reg [2:0] state = IDLE;

    // Data register
    reg [7:0] data = 0;

    // Bit counter
    reg [2:0] bitCounter = 0;

    always @(posedge txClk) begin
        case (state)
            IDLE: begin
                busy <= 0;
                done <= 0;
                out <= 1; // Idle state: High output
                if (en && start) begin
                    data <= in;
                    state <= START;
                    bitCounter <= 0;
                end
            end

            START: begin
                out <= 0; // Start bit
                state <= DATA;
            end

            DATA: begin
                out <= data[7 - bitCounter];
                bitCounter <= bitCounter + 1;
                if (bitCounter == 8) begin
                    state <= STOP;
                end
            end

            STOP: begin
                out <= 1; // Stop bit
                state <= IDLE;
                busy <= 1;
                done <= 1;
            end

            default: state <= IDLE;
        endcase
    end

    always @(posedge clk) begin
        if (state != IDLE) begin
            busy <= 1;
        end
    end

endmodule

// Top-level UART Module with adjusted receiver and transmitter
module Uart8 #(
    parameter CLOCK_RATE = 100000000,
    parameter BAUD_RATE = 9600,
    parameter TURBO_FRAMES = 0
)(
    input wire clk,

    input wire rxEn,
    input wire rx,
    output wire rxBusy,
    output wire rxDone,
    output wire rxErr,
    output wire [7:0] out,

    input wire txEn,
    input wire txStart,
    input wire [7:0] in,
    output wire txBusy,
    output wire txDone,
    output wire tx
);

    // Instantiate Baud Rate Generator
    wire rxClk;
    wire txClk;
    BaudRateGenerator baudGen(
        .clk(clk),
        .rxClk(rxClk),
        .txClk(txClk)
    );

    // Instantiate UART Receiver with rxClk
    Uart8Receiver receiver(
        .clk(clk),
        .rxClk(rxClk),
        .en(rxEn),
        .in(rx),
        .busy(rxBusy),
        .done(rxDone),
        .err(rxErr),
        .out(out)
    );

    // Instantiate UART Transmitter with txClk
    Uart8Transmitter transmitter(
        .clk(clk),
        .txClk(txClk),
        .en(txEn),
        .start(txStart),
        .in(in),
        .busy(txBusy),
        .done(txDone),
        .out(tx)
    );

endmodule

// Baud Rate Generator Module
module BaudRateGenerator #(
    parameter CLOCK_RATE = 100000000,
    parameter BAUD_RATE = 9600,
    parameter RX_OVERSAMPLE_RATE = 16
)(
    input wire clk,
    output wire rxClk,
    output wire txClk
);

    // Calculate the number of clock cycles per baud period for RX and TX
    localparam RX_BAUD_CYCLES = CLOCK_RATE / (BAUD_RATE * RX_OVERSAMPLE_RATE);
    localparam TX_BAUD_CYCLES = CLOCK_RATE / BAUD_RATE;

    // Counters for RX and TX baud rate generation
    reg [31:0] rxCounter = 0;
    reg [31:0] txCounter = 0;

    // Signals to generate RX and TX clocks
    reg rxClkEnable = 0;
    reg txClkEnable = 0;

    always @(posedge clk) begin
        // Increment RX counter
        rxCounter <= rxCounter + 1;
        
        // Generate RX clock
        if (rxCounter == RX_BAUD_CYCLES - 1) begin
            rxCounter <= 0;
            rxClkEnable <= ~rxClkEnable;
        end

        // Increment TX counter
        txCounter <= txCounter + 1;

        // Generate TX clock
        if (txCounter == TX_BAUD_CYCLES - 1) begin
            txCounter <= 0;
            txClkEnable <= ~txClkEnable;
        end
    end

    // Assign output clocks using continuous assignment
    assign rxClk = rxClkEnable;
    assign txClk = txClkEnable;

endmodule

Workspace/Sonar/8-bit UART/Uart8_tb.v
`timescale 100ns/1ns
`default_nettype none

`include "Uart8.v"

module test;

localparam CLOCK_FREQ = 12000000; // Alhambra board
localparam SIM_STEP_FREQ = 1 / 0.0000001 / 2; // this sim timescale 100ns

// for the simulation timeline:
// ratio SIM_STEP_FREQ MHz / CLOCK_FREQ MHz gives the output waveform in proper time
// (*but note all clocks and the timeline are approximate due to rounding)
localparam SIM_TIMESTEP_FACTOR = SIM_STEP_FREQ / CLOCK_FREQ;

localparam ENABLED_BAUD_CLOCK_STEPS = 17;

reg        clk;
reg        en_1;
reg        en_2;
reg        txStart_1;
reg        txStart_2;
wire       txBusy_1;
wire       txBusy_2;
wire       rxBusy_1;
wire       rxBusy_2;
wire       txDone_1;
wire       txDone_2;
wire       rxDone_1;
wire       rxDone_2;
wire       rxErr_1;
wire       rxErr_2;
reg [7:0]  txByte_1;
reg [7:0]  txByte_2;
wire [7:0] rxByte_1;
wire [7:0] rxByte_2;
wire       bus_wire_1_2;
wire       bus_wire_2_1;

Uart8 #(.CLOCK_RATE(CLOCK_FREQ)) uart1(
  .clk(clk),

  // rx interface
  .rxEn(en_2),
  .rx(bus_wire_2_1),
  .rxBusy(rxBusy_1),
  .rxDone(rxDone_1),
  .rxErr(rxErr_1),
  .out(rxByte_1),

  // tx interface
  .txEn(en_1),
  .txStart(txStart_1),
  .in(txByte_1),
  .txBusy(txBusy_1),
  .txDone(txDone_1),
  .tx(bus_wire_1_2)
);

Uart8 #(.CLOCK_RATE(CLOCK_FREQ)) uart2(
  .clk(clk),

  // rx interface
  .rxEn(en_1),
  .rx(bus_wire_1_2),
  .rxBusy(rxBusy_2),
  .rxDone(rxDone_2),
  .rxErr(rxErr_2),
  .out(rxByte_2),

  // tx interface
  .txEn(en_2),
  .txStart(txStart_2),
  .in(txByte_2),
  .txBusy(txBusy_2),
  .txDone(txDone_2),
  .tx(bus_wire_2_1)
);

initial clk = 1'b0;

always #SIM_TIMESTEP_FACTOR clk = ~clk;

integer t;

initial begin


  $dumpfile("test.vcd");
  $dumpvars(0, test);

#600
  en_1 = 1'b0;
  txStart_1 = 1'b0;
#600
  en_1 = 1'b1;

  txByte_1 = 8'b01000101;

  $display("            tx 1 data: %8b", txByte_1);

  for (t = 0; t < ENABLED_BAUD_CLOCK_STEPS; t++) begin
    // #1000 x 100ns == 0.1ms == 1 tx clock period (approximately) at 9600 baud
#1000
    case (t)
      1: begin
        txStart_1 = 1'b1;

        $display("%7.2fms | tx start: %d", $realtime/10000, txStart_1);
        $display("%7.2fms | tx busy: %d, tx done: %d", $realtime/10000, txBusy_1, txDone_1);
        $display("%7.2fms | rx 2 data: %8b", $realtime/10000, rxByte_2);
      end
      4: begin
        txStart_1 = 1'b0;

        $display("%7.2fms | tx start: %d", $realtime/10000, txStart_1);
      end
      13: begin
        // output is ready

        $display("%7.2fms | tx busy: %d, tx done: %d", $realtime/10000, txBusy_1, txDone_1);
        $display("%7.2fms | rx 2 data: %8b", $realtime/10000, rxByte_2);
      end
    endcase
  end

  en_1 = 1'b0;
#2400

  $finish();
end

endmodule

Workspace/Sonar/8-bit UART/test.vcd
$date
	Sat Mar 22 11:00:32 2025
$end
$version
	Icarus Verilog
$end
$timescale
	1ns
$end
$scope module test $end
$var wire 1 ! txDone_2 $end
$var wire 1 " txDone_1 $end
$var wire 1 # txBusy_2 $end
$var wire 1 $ txBusy_1 $end
$var wire 1 % rxErr_2 $end
$var wire 1 & rxErr_1 $end
$var wire 1 ' rxDone_2 $end
$var wire 1 ( rxDone_1 $end
$var wire 8 ) rxByte_2 [7:0] $end
$var wire 8 * rxByte_1 [7:0] $end
$var wire 1 + rxBusy_2 $end
$var wire 1 , rxBusy_1 $end
$var wire 1 - bus_wire_2_1 $end
$var wire 1 . bus_wire_1_2 $end
$var parameter 32 / CLOCK_FREQ $end
$var parameter 32 0 ENABLED_BAUD_CLOCK_STEPS $end
$var real 1 1 SIM_STEP_FREQ $end
$var real 1 2 SIM_TIMESTEP_FACTOR $end
$var reg 1 3 clk $end
$var reg 1 4 en_1 $end
$var reg 1 5 en_2 $end
$var reg 8 6 txByte_1 [7:0] $end
$var reg 8 7 txByte_2 [7:0] $end
$var reg 1 8 txStart_1 $end
$var reg 1 9 txStart_2 $end
$var integer 32 : t [31:0] $end
$scope module uart1 $end
$var wire 1 3 clk $end
$var wire 8 ; in [7:0] $end
$var wire 1 5 rxEn $end
$var wire 1 4 txEn $end
$var wire 1 8 txStart $end
$var wire 1 " txDone $end
$var wire 1 < txClk $end
$var wire 1 $ txBusy $end
$var wire 1 . tx $end
$var wire 1 & rxErr $end
$var wire 1 ( rxDone $end
$var wire 1 = rxClk $end
$var wire 1 , rxBusy $end
$var wire 1 - rx $end
$var wire 8 > out [7:0] $end
$var parameter 32 ? BAUD_RATE $end
$var parameter 32 @ CLOCK_RATE $end
$var parameter 32 A TURBO_FRAMES $end
$scope module baudGen $end
$var wire 1 3 clk $end
$var wire 1 = rxClk $end
$var wire 1 < txClk $end
$var parameter 32 B BAUD_RATE $end
$var parameter 32 C CLOCK_RATE $end
$var parameter 64 D RX_BAUD_CYCLES $end
$var parameter 32 E RX_OVERSAMPLE_RATE $end
$var parameter 32 F TX_BAUD_CYCLES $end
$var reg 1 G rxClkEnable $end
$var reg 32 H rxCounter [31:0] $end
$var reg 1 I txClkEnable $end
$var reg 32 J txCounter [31:0] $end
$upscope $end
$scope module receiver $end
$var wire 1 3 clk $end
$var wire 1 5 en $end
$var wire 1 = rxClk $end
$var wire 1 - in $end
$var parameter 32 K DATA $end
$var parameter 32 L IDLE $end
$var parameter 32 M RX_OVERSAMPLE_RATE $end
$var parameter 32 N START $end
$var parameter 32 O STOP $end
$var reg 3 P bitCounter [2:0] $end
$var reg 1 , busy $end
$var reg 8 Q data [7:0] $end
$var reg 1 ( done $end
$var reg 1 & err $end
$var reg 8 R out [7:0] $end
$var reg 4 S oversampleCounter [3:0] $end
$var reg 3 T state [2:0] $end
$upscope $end
$scope module transmitter $end
$var wire 1 3 clk $end
$var wire 1 4 en $end
$var wire 8 U in [7:0] $end
$var wire 1 8 start $end
$var wire 1 < txClk $end
$var parameter 32 V DATA $end
$var parameter 32 W IDLE $end
$var parameter 32 X START $end
$var parameter 32 Y STOP $end
$var parameter 32 Z TURBO_FRAMES $end
$var reg 3 [ bitCounter [2:0] $end
$var reg 1 $ busy $end
$var reg 8 \ data [7:0] $end
$var reg 1 " done $end
$var reg 1 . out $end
$var reg 3 ] state [2:0] $end
$upscope $end
$upscope $end
$scope module uart2 $end
$var wire 1 3 clk $end
$var wire 8 ^ in [7:0] $end
$var wire 1 . rx $end
$var wire 1 4 rxEn $end
$var wire 1 5 txEn $end
$var wire 1 9 txStart $end
$var wire 1 ! txDone $end
$var wire 1 _ txClk $end
$var wire 1 # txBusy $end
$var wire 1 - tx $end
$var wire 1 % rxErr $end
$var wire 1 ' rxDone $end
$var wire 1 ` rxClk $end
$var wire 1 + rxBusy $end
$var wire 8 a out [7:0] $end
$var parameter 32 b BAUD_RATE $end
$var parameter 32 c CLOCK_RATE $end
$var parameter 32 d TURBO_FRAMES $end
$scope module baudGen $end
$var wire 1 3 clk $end
$var wire 1 ` rxClk $end
$var wire 1 _ txClk $end
$var parameter 32 e BAUD_RATE $end
$var parameter 32 f CLOCK_RATE $end
$var parameter 64 g RX_BAUD_CYCLES $end
$var parameter 32 h RX_OVERSAMPLE_RATE $end
$var parameter 32 i TX_BAUD_CYCLES $end
$var reg 1 j rxClkEnable $end
$var reg 32 k rxCounter [31:0] $end
$var reg 1 l txClkEnable $end
$var reg 32 m txCounter [31:0] $end
$upscope $end
$scope module receiver $end
$var wire 1 3 clk $end
$var wire 1 4 en $end
$var wire 1 . in $end
$var wire 1 ` rxClk $end
$var parameter 32 n DATA $end
$var parameter 32 o IDLE $end
$var parameter 32 p RX_OVERSAMPLE_RATE $end
$var parameter 32 q START $end
$var parameter 32 r STOP $end
$var reg 3 s bitCounter [2:0] $end
$var reg 1 + busy $end
$var reg 8 t data [7:0] $end
$var reg 1 ' done $end
$var reg 1 % err $end
$var reg 8 u out [7:0] $end
$var reg 4 v oversampleCounter [3:0] $end
$var reg 3 w state [2:0] $end
$upscope $end
$scope module transmitter $end
$var wire 1 3 clk $end
$var wire 1 5 en $end
$var wire 8 x in [7:0] $end
$var wire 1 9 start $end
$var wire 1 _ txClk $end
$var parameter 32 y DATA $end
$var parameter 32 z IDLE $end
$var parameter 32 { START $end
$var parameter 32 | STOP $end
$var parameter 32 } TURBO_FRAMES $end
$var reg 3 ~ bitCounter [2:0] $end
$var reg 1 # busy $end
$var reg 8 !" data [7:0] $end
$var reg 1 ! done $end
$var reg 1 - out $end
$var reg 3 "" state [2:0] $end
$upscope $end
$upscope $end
$upscope $end
$enddefinitions $end
$comment Show the parameter values. $end
$dumpall
b0 }
b11 |
b1 {
b0 z
b10 y
b11 r
b1 q
b10000 p
b0 o
b10 n
b10100010110000 i
b10000 h
b1010001011 g
b101111101011110000100000000 f
b10010110000000 e
b0 d
b101101110001101100000000 c
b10010110000000 b
b0 Z
b11 Y
b1 X
b0 W
b10 V
b11 O
b1 N
b10000 M
b0 L
b10 K
b10100010110000 F
b10000 E
b1010001011 D
b101111101011110000100000000 C
b10010110000000 B
b0 A
b101101110001101100000000 @
b10010110000000 ?
r0.4166666666666667 2
r5000000 1
b1110 0
b101101110001101100000000 /
$end
#0
$dumpvars
b0 ""
b0 !"
b0 ~
bx x
b0 w
b0 v
bx u
b0 t
b0 s
b0 m
0l
b0 k
0j
bx a
0`
0_
bx ^
b0 ]
b0 \
b0 [
bx U
b0 T
b0 S
bx R
b0 Q
b0 P
b0 J
0I
b0 H
0G
bx >
0=
0<
bx ;
bx :
x9
x8
bx 7
bx 6
x5
x4
03
x.
x-
x,
x+
bx *
bx )
x(
x'
x&
x%
x$
x#
x"
x!
$end
#42
b1 J
b1 H
0,
b1 m
b1 k
0+
13
#84
03
#126
b10 m
b10 k
b10 J
b10 H
13
#168
03
#210
b11 J
b11 H
b11 m
b11 k
13
#252
03
#294
b100 m
b100 k
b100 J
b100 H
13
#336
03
#378
b101 J
b101 H
b101 m
b101 k
13
#420
03
#462
b110 m
b110 k
b110 J
b110 H
13
#504
03
#546
b111 J
b111 H
b111 m
b111 k
13
#588
03
#630
b1000 m
b1000 k
b1000 J
b1000 H
13
#672
03
#714
b1001 J
b1001 H
b1001 m
b1001 k
13
#756
03
#798
b1010 m
b1010 k
b1010 J
b1010 H
13
#840
03
#882
b1011 J
b1011 H
b1011 m
b1011 k
13
#924
03
#966
b1100 m
b1100 k
b1100 J
b1100 H
13
#1008
03
#1050
b1101 J
b1101 H
b1101 m
b1101 k
13
#1092
03
#1134
b1110 m
b1110 k
b1110 J
b1110 H
13
#1176
03
#1218
b1111 J
b1111 H
b1111 m
b1111 k
13
#1260
03
#1302
b10000 m
b10000 k
b10000 J
b10000 H
13
#1344
03
#1386
b10001 J
b10001 H
b10001 m
b10001 k
13
#1428
03
#1470
b10010 m
b10010 k
b10010 J
b10010 H
13
#1512
03
#1554
b10011 J
b10011 H
b10011 m
b10011 k
13
#1596
03
#1638
b10100 m
b10100 k
b10100 J
b10100 H
13
#1680
03
#1722
b10101 J
b10101 H
b10101 m
b10101 k
13
#1764
03
#1806
b10110 m
b10110 k
b10110 J
b10110 H
13
#1848
03
#1890
b10111 J
b10111 H
b10111 m
b10111 k
13
#1932
03
#1974
b11000 m
b11000 k
b11000 J
b11000 H
13
#2016
03
#2058
b11001 J
b11001 H
b11001 m
b11001 k
13
#2100
03
#2142
b11010 m
b11010 k
b11010 J
b11010 H
13
#2184
03
#2226
b11011 J
b11011 H
b11011 m
b11011 k
13
#2268
03
#2310
b11100 m
b11100 k
b11100 J
b11100 H
13
#2352
03
#2394
b11101 J
b11101 H
b11101 m
b11101 k
13
#2436
03
#2478
b11110 m
b11110 k
b11110 J
b11110 H
13
#2520
03
#2562
b11111 J
b11111 H
b11111 m
b11111 k
13
#2604
03
#2646
b100000 m
b100000 k
b100000 J
b100000 H
13
#2688
03
#2730
b100001 J
b100001 H
b100001 m
b100001 k
13
#2772
03
#2814
b100010 m
b100010 k
b100010 J
b100010 H
13
#2856
03
#2898
b100011 J
b100011 H
b100011 m
b100011 k
13
#2940
03
#2982
b100100 m
b100100 k
b100100 J
b100100 H
13
#3024
03
#3066
b100101 J
b100101 H
b100101 m
b100101 k
13
#3108
03
#3150
b100110 m
b100110 k
b100110 J
b100110 H
13
#3192
03
#3234
b100111 J
b100111 H
b100111 m
b100111 k
13
#3276
03
#3318
b101000 m
b101000 k
b101000 J
b101000 H
13
#3360
03
#3402
b101001 J
b101001 H
b101001 m
b101001 k
13
#3444
03
#3486
b101010 m
b101010 k
b101010 J
b101010 H
13
#3528
03
#3570
b101011 J
b101011 H
b101011 m
b101011 k
13
#3612
03
#3654
b101100 m
b101100 k
b101100 J
b101100 H
13
#3696
03
#3738
b101101 J
b101101 H
b101101 m
b101101 k
13
#3780
03
#3822
b101110 m
b101110 k
b101110 J
b101110 H
13
#3864
03
#3906
b101111 J
b101111 H
b101111 m
b101111 k
13
#3948
03
#3990
b110000 m
b110000 k
b110000 J
b110000 H
13
#4032
03
#4074
b110001 J
b110001 H
b110001 m
b110001 k
13
#4116
03
#4158
b110010 m
b110010 k
b110010 J
b110010 H
13
#4200
03
#4242
b110011 J
b110011 H
b110011 m
b110011 k
13
#4284
03
#4326
b110100 m
b110100 k
b110100 J
b110100 H
13
#4368
03
#4410
b110101 J
b110101 H
b110101 m
b110101 k
13
#4452
03
#4494
b110110 m
b110110 k
b110110 J
b110110 H
13
#4536
03
#4578
b110111 J
b110111 H
b110111 m
b110111 k
13
#4620
03
#4662
b111000 m
b111000 k
b111000 J
b111000 H
13
#4704
03
#4746
b111001 J
b111001 H
b111001 m
b111001 k
13
#4788
03
#4830
b111010 m
b111010 k
b111010 J
b111010 H
13
#4872
03
#4914
b111011 J
b111011 H
b111011 m
b111011 k
13
#4956
03
#4998
b111100 m
b111100 k
b111100 J
b111100 H
13
#5040
03
#5082
b111101 J
b111101 H
b111101 m
b111101 k
13
#5124
03
#5166
b111110 m
b111110 k
b111110 J
b111110 H
13
#5208
03
#5250
b111111 J
b111111 H
b111111 m
b111111 k
13
#5292
03
#5334
b1000000 m
b1000000 k
b1000000 J
b1000000 H
13
#5376
03
#5418
b1000001 J
b1000001 H
b1000001 m
b1000001 k
13
#5460
03
#5502
b1000010 m
b1000010 k
b1000010 J
b1000010 H
13
#5544
03
#5586
b1000011 J
b1000011 H
b1000011 m
b1000011 k
13
#5628
03
#5670
b1000100 m
b1000100 k
b1000100 J
b1000100 H
13
#5712
03
#5754
b1000101 J
b1000101 H
b1000101 m
b1000101 k
13
#5796
03
#5838
b1000110 m
b1000110 k
b1000110 J
b1000110 H
13
#5880
03
#5922
b1000111 J
b1000111 H
b1000111 m
b1000111 k
13
#5964
03
#6006
b1001000 m
b1001000 k
b1001000 J
b1001000 H
13
#6048
03
#6090
b1001001 J
b1001001 H
b1001001 m
b1001001 k
13
#6132
03
#6174
b1001010 m
b1001010 k
b1001010 J
b1001010 H
13
#6216
03
#6258
b1001011 J
b1001011 H
b1001011 m
b1001011 k
13
#6300
03
#6342
b1001100 m
b1001100 k
b1001100 J
b1001100 H
13
#6384
03
#6426
b1001101 J
b1001101 H
b1001101 m
b1001101 k
13
#6468
03
#6510
b1001110 m
b1001110 k
b1001110 J
b1001110 H
13
#6552
03
#6594
b1001111 J
b1001111 H
b1001111 m
b1001111 k
13
#6636
03
#6678
b1010000 m
b1010000 k
b1010000 J
b1010000 H
13
#6720
03
#6762
b1010001 J
b1010001 H
b1010001 m
b1010001 k
13
#6804
03
#6846
b1010010 m
b1010010 k
b1010010 J
b1010010 H
13
#6888
03
#6930
b1010011 J
b1010011 H
b1010011 m
b1010011 k
13
#6972
03
#7014
b1010100 m
b1010100 k
b1010100 J
b1010100 H
13
#7056
03
#7098
b1010101 J
b1010101 H
b1010101 m
b1010101 k
13
#7140
03
#7182
b1010110 m
b1010110 k
b1010110 J
b1010110 H
13
#7224
03
#7266
b1010111 J
b1010111 H
b1010111 m
b1010111 k
13
#7308
03
#7350
b1011000 m
b1011000 k
b1011000 J
b1011000 H
13
#7392
03
#7434
b1011001 J
b1011001 H
b1011001 m
b1011001 k
13
#7476
03
#7518
b1011010 m
b1011010 k
b1011010 J
b1011010 H
13
#7560
03
#7602
b1011011 J
b1011011 H
b1011011 m
b1011011 k
13
#7644
03
#7686
b1011100 m
b1011100 k
b1011100 J
b1011100 H
13
#7728
03
#7770
b1011101 J
b1011101 H
b1011101 m
b1011101 k
13
#7812
03
#7854
b1011110 m
b1011110 k
b1011110 J
b1011110 H
13
#7896
03
#7938
b1011111 J
b1011111 H
b1011111 m
b1011111 k
13
#7980
03
#8022
b1100000 m
b1100000 k
b1100000 J
b1100000 H
13
#8064
03
#8106
b1100001 J
b1100001 H
b1100001 m
b1100001 k
13
#8148
03
#8190
b1100010 m
b1100010 k
b1100010 J
b1100010 H
13
#8232
03
#8274
b1100011 J
b1100011 H
b1100011 m
b1100011 k
13
#8316
03
#8358
b1100100 m
b1100100 k
b1100100 J
b1100100 H
13
#8400
03
#8442
b1100101 J
b1100101 H
b1100101 m
b1100101 k
13
#8484
03
#8526
b1100110 m
b1100110 k
b1100110 J
b1100110 H
13
#8568
03
#8610
b1100111 J
b1100111 H
b1100111 m
b1100111 k
13
#8652
03
#8694
b1101000 m
b1101000 k
b1101000 J
b1101000 H
13
#8736
03
#8778
b1101001 J
b1101001 H
b1101001 m
b1101001 k
13
#8820
03
#8862
b1101010 m
b1101010 k
b1101010 J
b1101010 H
13
#8904
03
#8946
b1101011 J
b1101011 H
b1101011 m
b1101011 k
13
#8988
03
#9030
b1101100 m
b1101100 k
b1101100 J
b1101100 H
13
#9072
03
#9114
b1101101 J
b1101101 H
b1101101 m
b1101101 k
13
#9156
03
#9198
b1101110 m
b1101110 k
b1101110 J
b1101110 H
13
#9240
03
#9282
b1101111 J
b1101111 H
b1101111 m
b1101111 k
13
#9324
03
#9366
b1110000 m
b1110000 k
b1110000 J
b1110000 H
13
#9408
03
#9450
b1110001 J
b1110001 H
b1110001 m
b1110001 k
13
#9492
03
#9534
b1110010 m
b1110010 k
b1110010 J
b1110010 H
13
#9576
03
#9618
b1110011 J
b1110011 H
b1110011 m
b1110011 k
13
#9660
03
#9702
b1110100 m
b1110100 k
b1110100 J
b1110100 H
13
#9744
03
#9786
b1110101 J
b1110101 H
b1110101 m
b1110101 k
13
#9828
03
#9870
b1110110 m
b1110110 k
b1110110 J
b1110110 H
13
#9912
03
#9954
b1110111 J
b1110111 H
b1110111 m
b1110111 k
13
#9996
03
#10038
b1111000 m
b1111000 k
b1111000 J
b1111000 H
13
#10080
03
#10122
b1111001 J
b1111001 H
b1111001 m
b1111001 k
13
#10164
03
#10206
b1111010 m
b1111010 k
b1111010 J
b1111010 H
13
#10248
03
#10290
b1111011 J
b1111011 H
b1111011 m
b1111011 k
13
#10332
03
#10374
b1111100 m
b1111100 k
b1111100 J
b1111100 H
13
#10416
03
#10458
b1111101 J
b1111101 H
b1111101 m
b1111101 k
13
#10500
03
#10542
b1111110 m
b1111110 k
b1111110 J
b1111110 H
13
#10584
03
#10626
b1111111 J
b1111111 H
b1111111 m
b1111111 k
13
#10668
03
#10710
b10000000 m
b10000000 k
b10000000 J
b10000000 H
13
#10752
03
#10794
b10000001 J
b10000001 H
b10000001 m
b10000001 k
13
#10836
03
#10878
b10000010 m
b10000010 k
b10000010 J
b10000010 H
13
#10920
03
#10962
b10000011 J
b10000011 H
b10000011 m
b10000011 k
13
#11004
03
#11046
b10000100 m
b10000100 k
b10000100 J
b10000100 H
13
#11088
03
#11130
b10000101 J
b10000101 H
b10000101 m
b10000101 k
13
#11172
03
#11214
b10000110 m
b10000110 k
b10000110 J
b10000110 H
13
#11256
03
#11298
b10000111 J
b10000111 H
b10000111 m
b10000111 k
13
#11340
03
#11382
b10001000 m
b10001000 k
b10001000 J
b10001000 H
13
#11424
03
#11466
b10001001 J
b10001001 H
b10001001 m
b10001001 k
13
#11508
03
#11550
b10001010 m
b10001010 k
b10001010 J
b10001010 H
13
#11592
03
#11634
b10001011 J
b10001011 H
b10001011 m
b10001011 k
13
#11676
03
#11718
b10001100 m
b10001100 k
b10001100 J
b10001100 H
13
#11760
03
#11802
b10001101 J
b10001101 H
b10001101 m
b10001101 k
13
#11844
03
#11886
b10001110 m
b10001110 k
b10001110 J
b10001110 H
13
#11928
03
#11970
b10001111 J
b10001111 H
b10001111 m
b10001111 k
13
#12012
03
#12054
b10010000 m
b10010000 k
b10010000 J
b10010000 H
13
#12096
03
#12138
b10010001 J
b10010001 H
b10010001 m
b10010001 k
13
#12180
03
#12222
b10010010 m
b10010010 k
b10010010 J
b10010010 H
13
#12264
03
#12306
b10010011 J
b10010011 H
b10010011 m
b10010011 k
13
#12348
03
#12390
b10010100 m
b10010100 k
b10010100 J
b10010100 H
13
#12432
03
#12474
b10010101 J
b10010101 H
b10010101 m
b10010101 k
13
#12516
03
#12558
b10010110 m
b10010110 k
b10010110 J
b10010110 H
13
#12600
03
#12642
b10010111 J
b10010111 H
b10010111 m
b10010111 k
13
#12684
03
#12726
b10011000 m
b10011000 k
b10011000 J
b10011000 H
13
#12768
03
#12810
b10011001 J
b10011001 H
b10011001 m
b10011001 k
13
#12852
03
#12894
b10011010 m
b10011010 k
b10011010 J
b10011010 H
13
#12936
03
#12978
b10011011 J
b10011011 H
b10011011 m
b10011011 k
13
#13020
03
#13062
b10011100 m
b10011100 k
b10011100 J
b10011100 H
13
#13104
03
#13146
b10011101 J
b10011101 H
b10011101 m
b10011101 k
13
#13188
03
#13230
b10011110 m
b10011110 k
b10011110 J
b10011110 H
13
#13272
03
#13314
b10011111 J
b10011111 H
b10011111 m
b10011111 k
13
#13356
03
#13398
b10100000 m
b10100000 k
b10100000 J
b10100000 H
13
#13440
03
#13482
b10100001 J
b10100001 H
b10100001 m
b10100001 k
13
#13524
03
#13566
b10100010 m
b10100010 k
b10100010 J
b10100010 H
13
#13608
03
#13650
b10100011 J
b10100011 H
b10100011 m
b10100011 k
13
#13692
03
#13734
b10100100 m
b10100100 k
b10100100 J
b10100100 H
13
#13776
03
#13818
b10100101 J
b10100101 H
b10100101 m
b10100101 k
13
#13860
03
#13902
b10100110 m
b10100110 k
b10100110 J
b10100110 H
13
#13944
03
#13986
b10100111 J
b10100111 H
b10100111 m
b10100111 k
13
#14028
03
#14070
b10101000 m
b10101000 k
b10101000 J
b10101000 H
13
#14112
03
#14154
b10101001 J
b10101001 H
b10101001 m
b10101001 k
13
#14196
03
#14238
b10101010 m
b10101010 k
b10101010 J
b10101010 H
13
#14280
03
#14322
b10101011 J
b10101011 H
b10101011 m
b10101011 k
13
#14364
03
#14406
b10101100 m
b10101100 k
b10101100 J
b10101100 H
13
#14448
03
#14490
b10101101 J
b10101101 H
b10101101 m
b10101101 k
13
#14532
03
#14574
b10101110 m
b10101110 k
b10101110 J
b10101110 H
13
#14616
03
#14658
b10101111 J
b10101111 H
b10101111 m
b10101111 k
13
#14700
03
#14742
b10110000 m
b10110000 k
b10110000 J
b10110000 H
13
#14784
03
#14826
b10110001 J
b10110001 H
b10110001 m
b10110001 k
13
#14868
03
#14910
b10110010 m
b10110010 k
b10110010 J
b10110010 H
13
#14952
03
#14994
b10110011 J
b10110011 H
b10110011 m
b10110011 k
13
#15036
03
#15078
b10110100 m
b10110100 k
b10110100 J
b10110100 H
13
#15120
03
#15162
b10110101 J
b10110101 H
b10110101 m
b10110101 k
13
#15204
03
#15246
b10110110 m
b10110110 k
b10110110 J
b10110110 H
13
#15288
03
#15330
b10110111 J
b10110111 H
b10110111 m
b10110111 k
13
#15372
03
#15414
b10111000 m
b10111000 k
b10111000 J
b10111000 H
13
#15456
03
#15498
b10111001 J
b10111001 H
b10111001 m
b10111001 k
13
#15540
03
#15582
b10111010 m
b10111010 k
b10111010 J
b10111010 H
13
#15624
03
#15666
b10111011 J
b10111011 H
b10111011 m
b10111011 k
13
#15708
03
#15750
b10111100 m
b10111100 k
b10111100 J
b10111100 H
13
#15792
03
#15834
b10111101 J
b10111101 H
b10111101 m
b10111101 k
13
